unified_agent_protocol-1.0.1.dist-info/licenses/LICENSE
unified_agent_protocol-1.0.1.dist-info/licenses/NOTICE
unifiedagentprotocol/__init__.py
unifiedagentprotocol/cli/__init__.py
unifiedagentprotocol/cli/__main__.py
unifiedagentprotocol/export/__init__.py
unifiedagentprotocol/export/to_a2a.py
unifiedagentprotocol/export/to_mcp.py
unifiedagentprotocol/export/to_openapi.py
unifiedagentprotocol/models/__init__.py
unifiedagentprotocol/models/agent.py
unifiedagentprotocol/models/common.py
unifiedagentprotocol/models/tool.py
unifiedagentprotocol/parser/__init__.py
unifiedagentprotocol/parser/langchain.py
unifiedagentprotocol/parser/openapi.py
unifiedagentprotocol/parser/openwebui.py
unifiedagentprotocol/parser/swagger.py
unified_agent_protocol-1.0.1.dist-info/METADATA
unified_agent_protocol-1.0.1.dist-info/WHEEL
unified_agent_protocol-1.0.1.dist-info/entry_points.txt
unified_agent_protocol-1.0.1.dist-info/top_level.txt
unified_agent_protocol-1.0.1.dist-info/RECORD
