Metadata-Version: 2.4
Name: unified-agent-protocol
Version: 1.0.1
Summary: Unified Agent Protocol Core SDK - Universal interoperability layer for AI agents and tools
Home-page: https://github.com/WhoMeta-Inc/unifiedagentprotocol
Author: WhoMeta
Author-email: "WhoMeta Inc." <opensource@whometa.com>
Maintainer-email: WhoMeta Labs <labs@whometa.com>
License: Apache-2.0
Project-URL: Homepage, https://www.whometa.io
Project-URL: Repository, https://github.com/WhoMeta-Inc/unifiedagentprotocol
Project-URL: Bug Tracker, https://github.com/WhoMeta-Inc/unifiedagentprotocol/issues
Project-URL: Changelog, https://github.com/WhoMeta-Inc/unifiedagentprotocol/blob/main/CHANGELOG.md
Project-URL: Source Code, https://github.com/WhoMeta-Inc/unifiedagentprotocol
Project-URL: Release Notes, https://github.com/WhoMeta-Inc/unifiedagentprotocol/releases
Keywords: ai-agents,protocol,interoperability,agent-tools,mcp,a2a,openapi,langchain,openwebui,agent-orchestration,tool-integration,sdk
Classifier: Development Status :: 3 - Alpha
Classifier: Intended Audience :: Developers
Classifier: Intended Audience :: Science/Research
Classifier: Intended Audience :: Information Technology
Classifier: Topic :: Software Development :: Libraries :: Python Modules
Classifier: Topic :: Scientific/Engineering :: Artificial Intelligence
Classifier: Topic :: Internet :: WWW/HTTP :: Dynamic Content
Classifier: Topic :: System :: Distributed Computing
Classifier: License :: OSI Approved :: Apache Software License
Classifier: Programming Language :: Python :: 3
Classifier: Programming Language :: Python :: 3.10
Classifier: Programming Language :: Python :: 3.11
Classifier: Programming Language :: Python :: 3.12
Classifier: Programming Language :: Python :: 3.13
Classifier: Programming Language :: Python :: 3 :: Only
Classifier: Operating System :: OS Independent
Classifier: Environment :: Console
Classifier: Environment :: Web Environment
Classifier: Framework :: Pydantic
Classifier: Framework :: AsyncIO
Classifier: Natural Language :: English
Classifier: Typing :: Typed
Requires-Python: >=3.10
License-File: LICENSE
License-File: NOTICE
Requires-Dist: pydantic<3.0,>=2.0
Requires-Dist: typer<1.0,>=0.9.0
Requires-Dist: requests<3.0,>=2.28.0
Requires-Dist: jsonschema<5.0,>=4.17.0
Requires-Dist: pyyaml<7.0,>=6.0
Requires-Dist: rich<14.0,>=13.0.0
Provides-Extra: dev
Requires-Dist: pytest>=7.4.0; extra == "dev"
Requires-Dist: pytest-cov>=4.1.0; extra == "dev"
Requires-Dist: pytest-asyncio>=0.21.0; extra == "dev"
Requires-Dist: black>=23.7.0; extra == "dev"
Requires-Dist: isort>=5.12.0; extra == "dev"
Requires-Dist: flake8>=6.0.0; extra == "dev"
Requires-Dist: mypy>=1.5.0; extra == "dev"
Requires-Dist: pre-commit>=3.3.0; extra == "dev"
Requires-Dist: tox>=4.6.0; extra == "dev"
Provides-Extra: docs
Requires-Dist: mkdocs>=1.5.0; extra == "docs"
Requires-Dist: mkdocs-material>=9.1.0; extra == "docs"
Requires-Dist: mkdocstrings[python]>=0.22.0; extra == "docs"
Requires-Dist: mkdocs-autorefs>=0.4.0; extra == "docs"
Provides-Extra: async
Requires-Dist: aiohttp<4.0,>=3.8.0; extra == "async"
Requires-Dist: asyncio-throttle<2.0,>=1.0.0; extra == "async"
Provides-Extra: formats
Requires-Dist: toml>=0.10.0; extra == "formats"
Requires-Dist: xmltodict>=0.13.0; extra == "formats"
Requires-Dist: protobuf<5.0,>=4.0.0; extra == "formats"
Provides-Extra: performance
Requires-Dist: orjson<4.0,>=3.9.0; extra == "performance"
Requires-Dist: msgpack<2.0,>=1.0.0; extra == "performance"
Provides-Extra: all
Requires-Dist: unified-agent-protocol[async,dev,docs,formats,performance]; extra == "all"
Dynamic: license-file
